Stormdash.py
Stormspotter.py
stormspotter/__init__.py
stormspotter/cloud.cfg
stormspotter/__pycache__/__init__.cpython-38.pyc
stormspotter/dash/__init__.py
stormspotter/dash/__pycache__/__init__.cpython-38.pyc
stormspotter/dash/assets/CascadiaMono.ttf
stormspotter/dash/assets/favicon.ico
stormspotter/dash/assets/filter.png
stormspotter/dash/assets/graph.png
stormspotter/dash/assets/settings.png
stormspotter/dash/assets/stormdash.css
stormspotter/dash/assets/images/aadapp.png
stormspotter/dash/assets/images/aadgroup.png
stormspotter/dash/assets/images/aadsp.png
stormspotter/dash/assets/images/aaduser.png
stormspotter/dash/assets/images/appservice.png
stormspotter/dash/assets/images/disks.png
stormspotter/dash/assets/images/generic.png
stormspotter/dash/assets/images/icon-graph.png
stormspotter/dash/assets/images/ip.png
stormspotter/dash/assets/images/ipconf.png
stormspotter/dash/assets/images/kv.png
stormspotter/dash/assets/images/loadb.png
stormspotter/dash/assets/images/nic.png
stormspotter/dash/assets/images/none.png
stormspotter/dash/assets/images/nsg.png
stormspotter/dash/assets/images/rg.png
stormspotter/dash/assets/images/rule.png
stormspotter/dash/assets/images/sf.png
stormspotter/dash/assets/images/sqldb.png
stormspotter/dash/assets/images/sqlserver.png
stormspotter/dash/assets/images/storage.png
stormspotter/dash/assets/images/sub.png
stormspotter/dash/assets/images/tenant.png
stormspotter/dash/assets/images/vm.png
stormspotter/dash/assets/images/vnet.png
stormspotter/dash/core/__init__.py
stormspotter/dash/core/context.py
stormspotter/dash/core/neo4j.py
stormspotter/dash/core/parsers.py
stormspotter/dash/core/queries.py
stormspotter/dash/core/resources.py
stormspotter/dash/core/__pycache__/__init__.cpython-38.pyc
stormspotter/dash/core/__pycache__/context.cpython-38.pyc
stormspotter/dash/core/__pycache__/neo4j.cpython-38.pyc
stormspotter/dash/core/__pycache__/parsers.cpython-38.pyc
stormspotter/dash/core/__pycache__/queries.cpython-38.pyc
stormspotter-1.0.0a0.dist-info/LICENSE
stormspotter-1.0.0a0.dist-info/LICENSE-3rdParty.md
stormspotter-1.0.0a0.dist-info/METADATA
stormspotter-1.0.0a0.dist-info/WHEEL
stormspotter-1.0.0a0.dist-info/entry_points.txt
stormspotter-1.0.0a0.dist-info/top_level.txt
stormspotter-1.0.0a0.dist-info/RECORD
