Metadata-Version: 2.1
Name: stormspotter
Version: 1.0.0a0
Summary: Azure Red Team tool for graphing Azure and Azure Active Directory objects
Home-page: https://github.com/Azure/Stormspotter
Author: Azure Red Team
License: UNKNOWN
Platform: UNKNOWN
Classifier: Development Status :: 3 - Alpha
Classifier: Programming Language :: Python :: 3.8
Classifier: Operating System :: OS Independent
Classifier: Framework :: Dash
Classifier: License :: OSI Approved :: MIT License
Requires-Python: >=3.8
Requires-Dist: azure-cli-core (==2.5.1)
Requires-Dist: azure-mgmt-authorization (==0.60.0)
Requires-Dist: azure-mgmt-core (==1.0.0)
Requires-Dist: azure-mgmt-resource (==9.0.0)
Requires-Dist: dash (==1.12.0)
Requires-Dist: dash-bootstrap-components (==0.9.2)
Requires-Dist: dash-cytoscape (==0.1.1)
Requires-Dist: dash-daq (==0.5.0)
Requires-Dist: neo4j (==1.7.6)
Requires-Dist: pkginfo (==1.5.0.1)
Requires-Dist: shiv (==0.1.2)
Requires-Dist: watchdog (==0.10.2)
